LICENSE
MANIFEST.in
basesetup.py
setup.py
examples/.gitignore
examples/Clustering-Comparison.ipynb
examples/Fs-Peptide-command-line.ipynb
examples/Fs-Peptide-in-RAM.ipynb
examples/Fs-Peptide-with-Pipeline.ipynb
examples/Fs-Peptide-with-dataset.ipynb
examples/GMRQ-Model-Selection.ipynb
examples/LICENSE.md
examples/Ligand-Featurization.ipynb
examples/Ward-Clustering.ipynb
examples/tICA-vs-PCA.ipynb
examples/advanced/bayesian-msm.ipynb
examples/advanced/hmm-and-msm.ipynb
examples/advanced/implied-timescales.ipynb
examples/advanced/plot-tica-heatmap.ipynb
examples/advanced/quadwell-n-states.ipynb
examples/advanced/quadwell.ipynb
examples/advanced/uncertainty.ipynb
msmbuilder/__init__.py
msmbuilder/base.py
msmbuilder/cmdline.py
msmbuilder/dataset.py
msmbuilder/version.py
msmbuilder/cluster/_kmedoids.pyx
msmbuilder/cluster/src/kmedoids.cc
msmbuilder/hmm/gaussian.pyx
msmbuilder/hmm/vonmises.pyx
msmbuilder/hmm/cephes/chbevl.c
msmbuilder/hmm/cephes/i0.c
msmbuilder/hmm/src/GaussianHMMFitter.cpp
msmbuilder/hmm/src/VonMisesHMMFitter.cpp
msmbuilder/libdistance/libdistance.pyx
msmbuilder/msm/_markovstatemodel.pyx
msmbuilder/msm/_metzner_mcmc_fast.pyx
msmbuilder/msm/_ratematrix.pyx
msmbuilder/msm/src/metzner_mcmc.c
msmbuilder/msm/src/transmat_mle_prinz.c
msmbuilder/tests/test_cyblas.pyx
msmbuilder/cluster/__init__.py
msmbuilder/cluster/_kmedoids.pyx
msmbuilder/cluster/agglomerative.py
msmbuilder/cluster/apm.py
msmbuilder/cluster/base.py
msmbuilder/cluster/kcenters.py
msmbuilder/cluster/kmedoids.py
msmbuilder/cluster/minibatchkmedoids.py
msmbuilder/cluster/ndgrid.py
msmbuilder/cluster/regularspatial.py
msmbuilder/cluster/src/kmedoids.cc
msmbuilder/cluster/src/kmedoids.h
msmbuilder/commands/__init__.py
msmbuilder/commands/atom_indices.py
msmbuilder/commands/convert_chunked_project.py
msmbuilder/commands/example_datasets.py
msmbuilder/commands/featurizer.py
msmbuilder/commands/fit.py
msmbuilder/commands/fit_transform.py
msmbuilder/commands/implied_timescales.py
testmsm.egg-info/PKG-INFO
testmsm.egg-info/SOURCES.txt
testmsm.egg-info/dependency_links.txt
testmsm.egg-info/entry_points.txt
testmsm.egg-info/not-zip-safe
testmsm.egg-info/top_level.txt